README.md
setup.py
selenium_pages/__init__.py
selenium_pages/condition.py
selenium_pages/page.py
selenium_pages/page_manager.py
selenium_pages/page_test.py
selenium_pages.egg-info/PKG-INFO
selenium_pages.egg-info/SOURCES.txt
selenium_pages.egg-info/dependency_links.txt
selenium_pages.egg-info/requires.txt
selenium_pages.egg-info/top_level.txt